{"is_source_file": false, "format": "", "description": "", "external_files": [], "external_methods": [], "published": [], "classes": [], "methods": [], "calls": [], "search-terms": [], "state": 2, "file_id": 11, "knowledge_revision": 21, "git_revision": "d23021164dbe0ac35337846a2c91f7180d0ddb91", "hash": "69cdc7c8ed2ccc70f197b8306003836d", "format-version": 4, "code-base-name": "frontend_slidev", "filename": "frontend_slidev/README.md", "revision_history": [{"21": "d23021164dbe0ac35337846a2c91f7180d0ddb91"}]}